Workbook

Sheet Plan de pruebas
A1: CP | B1: RF | C1: Descripción | D1: Input | E1: Resultado esperado | F1: Resultado obtenido | G1: Observación | H1: Estado
A2: CP1 | B2: RF-001 | C2: Validar restricción ORM contra salario negativo. | D2: salario base ORM: -1 | E2: La base de datos rechaza el registro con IntegrityError. | F2: Excepción: IntegrityError | G2: Prueba automatizada: ValidacionesGestionUsuarioTest.test_constraint_impide_salario_negativo_por_orm | H2: Aprobado
A3: CP2 | B3: RF-001 | C3: Validar que se guarde identificación de 12 dígitos. | D3: identificación: '123456789012' | E3: El registro guarda identificación 123456789012. | F3: Identificación guardada: 123456789012 | G3: Prueba automatizada: ValidacionesGestionUsuarioTest.test_creacion_guarda_identificacion_de_12_digitos | H3: Aprobado
A4: CP3 | B4: RF-001 | C4: Validar fecha mínima de ingreso. | D4: fecha de ingreso: '1949-12-31' | E4: El formulario informa que la fecha no puede ser anterior a 1950. | F4: Mensaje mostrado: La fecha de ingreso no puede ser anterior a 1950. | G4: Prueba automatizada: ValidacionesGestionUsuarioTest.test_fecha_ingreso_anterior_a_1950 | H4: Aprobado
A5: CP4 | B5: RF-001 | C5: Validar que fecha de ingreso futura sea rechazada. | D5: fecha de ingreso: mañana | E5: El formulario informa que la fecha no puede ser posterior a hoy. | F5: Mensaje mostrado: La fecha de ingreso no puede ser posterior a hoy. | G5: Prueba automatizada: ValidacionesGestionUsuarioTest.test_fecha_ingreso_futura | H5: Aprobado
A6: CP5 | B6: RF-001 | C6: Validar que identificación rechace letras. | D6: identificación: '91A0616' | E6: El formulario informa que identificación solo admite números. | F6: Mensaje mostrado: La identificación solo puede contener números. | G6: Prueba automatizada: ValidacionesGestionUsuarioTest.test_identificacion_con_letras | H6: Aprobado
A7: CP6 | B7: RF-001 | C7: Validar longitud mínima de identificación. | D7: identificación: '1234' | E7: El formulario informa que identificación debe tener entre 5 y 12 dígitos. | F7: Mensaje mostrado: La identificación debe tener entre 5 y 12 dígitos. | G7: Prueba automatizada: ValidacionesGestionUsuarioTest.test_identificacion_corta | H7: Aprobado
A8: CP7 | B8: RF-001 | C8: Validar que identificación duplicada sea rechazada. | D8: identificación: '9160616'; ya registrada | E8: El formulario informa que identificación ya existe. | F8: Mensaje mostrado: Ya existe un usuario con esa identificación. | G8: Prueba automatizada: ValidacionesGestionUsuarioTest.test_identificacion_duplicada | H8: Aprobado
A9: CP8 | B9: RF-001 | C9: Validar que identificación no empiece en cero. | D9: identificación: '01234' | E9: El formulario informa que identificación no puede empezar con cero. | F9: Mensaje mostrado: La identificación no puede empezar con cero. | G9: Prueba automatizada: ValidacionesGestionUsuarioTest.test_identificacion_empieza_en_cero | H9: Aprobado
A10: CP9 | B10: RF-001 | C10: Validar que nombres rechace números. | D10: nombres: 'Ana2' | E10: El formulario informa que nombres solo admite letras y espacios. | F10: Mensaje mostrado: El campo nombres solo puede contener letras y espacios. | G10: Prueba automatizada: ValidacionesGestionUsuarioTest.test_nombres_solo_letras | H10: Aprobado
A11: CP10 | B11: RF-001 | C11: Validar salario base cero. | D11: salario base: '0' | E11: El formulario informa que el salario debe ser mayor que cero. | F11: Mensaje mostrado: El salario base debe ser mayor que cero. | G11: Prueba automatizada: ValidacionesGestionUsuarioTest.test_salario_cero | H11: Aprobado
A12: CP11 | B12: RF-001 | C12: Validar conversión decimal del salario base. | D12: salario base: '1500000,50' | E12: El valor normalizado es 1500000.50. | F12: Salario normalizado: 1500000.50 | G12: Prueba automatizada: ValidacionesGestionUsuarioTest.test_salario_decimal_normalizado | H12: Aprobado
... A307: CP306 | B307: RNF-016 | C307: Validar que el sembrado de datos de carga exija confirmación explícita. | D307: sembrar_datos_carga sin --confirmar | E307: Agrega --confirmar para sembrar datos de carga. | F307: Mensaje: Agrega --confirmar para sembrar datos de carga. | G307: Prueba automatizada: SembrarDatosCargaTest.test_requiere_confirmacion | H307: Aprobado

Sheet Requisitos
A1: RF/RNF | B1: Descripción | C1: Cantidad de CP | D1: Aprobados
A2: RF-001 | B2: Registro de empleados | C2: =COUNTIF('Plan de pruebas'!$B:$B,A2) | D2: =COUNTIFS('Plan de pruebas'!$B:$B,A2,'Plan de pruebas'!$H:$H,"Aprobado")
A3: RF-002 | B3: Registro de horas extra | C3: =COUNTIF('Plan de pruebas'!$B:$B,A3) | D3: =COUNTIFS('Plan de pruebas'!$B:$B,A3,'Plan de pruebas'!$H:$H,"Aprobado")
A4: RF-003 | B4: Solicitud de certificados laborales | C4: =COUNTIF('Plan de pruebas'!$B:$B,A4) | D4: =COUNTIFS('Plan de pruebas'!$B:$B,A4,'Plan de pruebas'!$H:$H,"Aprobado")
A5: RF-004 | B5: Consulta de nómina, reportes y PDF | C5: =COUNTIF('Plan de pruebas'!$B:$B,A5) | D5: =COUNTIFS('Plan de pruebas'!$B:$B,A5,'Plan de pruebas'!$H:$H,"Aprobado")
A6: RF-005 | B6: Bonificaciones configurables | C6: =COUNTIF('Plan de pruebas'!$B:$B,A6) | D6: =COUNTIFS('Plan de pruebas'!$B:$B,A6,'Plan de pruebas'!$H:$H,"Aprobado")
A7: RF-006 | B7: Frecuencia y método de pago | C7: =COUNTIF('Plan de pruebas'!$B:$B,A7) | D7: =COUNTIFS('Plan de pruebas'!$B:$B,A7,'Plan de pruebas'!$H:$H,"Aprobado")
A8: RF-007 | B8: Aprobación de solicitudes | C8: =COUNTIF('Plan de pruebas'!$B:$B,A8) | D8: =COUNTIFS('Plan de pruebas'!$B:$B,A8,'Plan de pruebas'!$H:$H,"Aprobado")
A9: RF-008 | B9: Cálculo de nómina y pre-nómina | C9: =COUNTIF('Plan de pruebas'!$B:$B,A9) | D9: =COUNTIFS('Plan de pruebas'!$B:$B,A9,'Plan de pruebas'!$H:$H,"Aprobado")
A10: RF-009 | B10: Registro de usuarios y contraseña cifrada | C10: =COUNTIF('Plan de pruebas'!$B:$B,A10) | D10: =COUNTIFS('Plan de pruebas'!$B:$B,A10,'Plan de pruebas'!$H:$H,"Aprobado")
A11: RF-010 | B11: Autenticación con correo y contraseña | C11: =COUNTIF('Plan de pruebas'!$B:$B,A11) | D11: =COUNTIFS('Plan de pruebas'!$B:$B,A11,'Plan de pruebas'!$H:$H,"Aprobado")
A12: RF-011 | B12: Cambio de contraseña | C12: =COUNTIF('Plan de pruebas'!$B:$B,A12) | D12: =COUNTIFS('Plan de pruebas'!$B:$B,A12,'Plan de pruebas'!$H:$H,"Aprobado")
A13: RF-012 | B13: Perfil de usuario | C13: =COUNTIF('Plan de pruebas'!$B:$B,A13) | D13: =COUNTIFS('Plan de pruebas'!$B:$B,A13,'Plan de pruebas'!$H:$H,"Aprobado")
... A27: RNF-016 | B27: Volumen de 200 empleados | C27: =COUNTIF('Plan de pruebas'!$B:$B,A27) | D27: =COUNTIFS('Plan de pruebas'!$B:$B,A27,'Plan de pruebas'!$H:$H,"Aprobado")
